./.gitignore
./LICENSE
./PKG-INFO
./README.md
./example.mcp.json
./pyproject.toml
./relay.md
./relay_server.py
./requirements.txt
./screenshot.png
./server.json
./.claude/commands/relay.md
mcp_server_relay-1.2.4.dist-info/METADATA
mcp_server_relay-1.2.4.dist-info/WHEEL
mcp_server_relay-1.2.4.dist-info/entry_points.txt
mcp_server_relay-1.2.4.dist-info/licenses/LICENSE
mcp_server_relay-1.2.4.dist-info/RECORD
