Metadata-Version: 2.4
Name: mcp-server-relay
Version: 1.2.4
Summary: MCP relay server for Claude Desktop <-> Claude Code communication
Project-URL: Homepage, https://github.com/mhcoen/mcp-relay
Project-URL: Repository, https://github.com/mhcoen/mcp-relay
Author-email: Michael Coen <mhcoen@gmail.com>
License-Expression: MIT
License-File: LICENSE
Keywords: anthropic,claude,mcp,relay
Classifier: Development Status :: 4 - Beta
Classifier: Intended Audience :: Developers
Classifier: License :: OSI Approved :: MIT License
Classifier: Programming Language :: Python :: 3
Classifier: Programming Language :: Python :: 3.9
Classifier: Programming Language :: Python :: 3.10
Classifier: Programming Language :: Python :: 3.11
Classifier: Programming Language :: Python :: 3.12
Requires-Python: >=3.9
Requires-Dist: mcp
